{
  "diagonal": [
    "15\"",
    "15.6\"",
    "17\"",
    "18.5\"",
    "19\"",
    "19.5\"",
    "20.1\"",
    "21.5\"",
    "22\"",
    "22.5\"",
    "23\"",
    "23.5\"",
    "23.6\"",
    "23.8\"",
    "24\"",
    "24.1\"",
    "24.5\"",
    "25\"",
    "27\"",
    "27.9\"",
    "28\"",
    "29\"",
    "29.5\"",
    "30\"",
    "31\"",
    "31.5\"",
    "32\"",
    "34\"",
    "35\"",
    "37.5\"",
    "40\"",
    "43\"",
    "48.8\"",
    "48.9\"",
    "49\"",
    "50\"",
    "55\"",
    "60\"",
    "80\""
  ],
  "brightness": [
    "250 кд/м²",
    "300 кд/м²",
    "Стандартна: 250 кд/м²<br>Мінімальна: 200 кд/м²",
    "350 кд/м²",
    "600 кд/м² (Пікова)",
    "300 кд/м2",
    "350 кд/м2",
    "320 кд/м²",
    "Типова: 270 кд/м²<br>Мінімальна: 225 кд/м²",
    "250 кд/м2",
    "360 кд/м²",
    "400 кд/м²",
    "450 кд/м²",
    "420 кд/м²",
    "200 кд/м2",
    "350",
    "550 кд/м²",
    "600 кд/м²",
    "250 cd/m²",
    "200 кд/м²",
    "200 Cd/m",
    "250",
    "300 кд/м<sup><small>2</small></sup>",
    "400 кд/м2",
    "350 кд/м² (типова)/400 кд/м² (пікова)",
    "1000 кд/м²",
    "350 cd/m²",
    "460",
    "750 кд/м2",
    "300 Cd/m",
    "600",
    "400",
    "1200 кд/м2",
    "350 кд/м² - власний<br>400 кд/м² - пік (у режимі HDR)",
    "444 кд/м2",
    "200",
    "450 кд/м2",
    "700",
    "320 кд/м2",
    "500 кд/м²",
    "300 Кд/м²",
    "220 кд/м²",
    "230 кд/м2",
    "350 Кд/м2",
    "250  кд/м²",
    "550 кд/м2",
    "300 кд/м² (номінал)"
  ],
  "resolution": [
    "1280 х 1024",
    "1360х768",
    "1366x768",
    "1440x900",
    "1600 х 900",
    "1680x1050",
    "1920x1080 (FullHD)",
    "1920x1200",
    "2560x1080",
    "2560x1440 (2K QHD)",
    "2560x1600",
    "3440x1440",
    "3840x1600",
    "3840x2160 (4K UltraHD)",
    "4096x2160",
    "5120x1440",
    "5120x2160 (5K UltraHD)"
  ],
  "matrixSpeed": [
    "1 мс (GtG)",
    "5 мс",
    "1 мс MPRT",
    "4 мс (GtG)",
    "1 мс",
    "6 мс",
    "5 мс (GTG)",
    "1 мс (GTG)",
    "4 мс",
    "1 мс (MPRT)",
    "5 мс (Gray to Gray)",
    "8 мс у звичайному режимі<br>5 мс (від сірого до сірого) у прискореному режимі",
    "4 мс (GTG)",
    "1 мс Overdrive<br>5 мс Typycal",
    "4 ms (Extreme mode)",
    "5 мс (от серого к серому в экстремальном режиме)<br>8 мс (от серого к серому в ускоренном режиме)",
    "5 мс (сірий до сірого)",
    "0.5 мс",
    "1 мс (сірий до сірого)",
    "8 мс",
    "1 мс (MPRT)/2 мс (GTG)",
    "8 мс (номінал, звичайний режим)<br>5 мс (номінал, прискорений режим) (від сірого до сірого)",
    "8 мс (звичайний режим)<br> 5 мс (прискорений режим) (від сірого до сірого)",
    "0.8 мс",
    "1 мс (Gray to Gray)",
    "5 мс GTG",
    "8 мс (звичайний режим); 5 мс (прискорений режим) (від сірого до сірого)",
    "8 мс (обычный режим); <br/> 5 мс (ускоренный режим) (от серого к серому)",
    "1 мс (методика MPRT)",
    "4 мс GtG",
    "14 мс, 4 мс (GtG)",
    "1 мс (MPRT)<br>4 мс (від сірого до сірого) в екстремальному режимі",
    "5 мс (звичайний режим, від сірого до сірого, номінал)",
    "5",
    "4 мс (сірий до сірого)",
    "1 мс GTG",
    "4мс (GtG)",
    "5.4мс (G&G)",
    "5 мс (GtG)",
    "1мс",
    "3 мс",
    "12 мс, 4 мс (GtG)",
    "14 мс, 5 мс (GTG)",
    "4 мс (сірий до сірого)<br>1 мс (MPRT)",
    "4",
    "4 мс (Extreme mode)",
    "5мс",
    "1мс (MPRT)",
    "4мс",
    "1 мс (ULMB)",
    "2 мс",
    "1мс (GtG)",
    "0.5 мс (GTG)",
    "1 мс (сірий-сірий)",
    "4мс (GtG), 1мс (MPRT)",
    "5мс (GtG)",
    "25 мс",
    "4мс(G&amp;G)",
    "10",
    "6мс",
    "4мс(G&G)",
    "7 мс",
    "5мс(G&G)",
    "8мс",
    "5мс (G&G)",
    "6",
    "3мс",
    "13мс (G&G)",
    "1 мс VRB",
    "1",
    "12 мс",
    "1 мс (VRB)/4 мс GTG",
    "1 мс Overdrive 5 мс Typycal",
    "0.5",
    "8 мс (сірий до сірого/чорний до білого)",
    "5мс (G&amp;G)",
    "8 ms",
    "13мс (GtG)",
    "1 мс (від сірого до сірого) в екстремальному режимі",
    "14 мс",
    "13 мс",
    "5 ms",
    "0.5мс",
    "14мс",
    "16мс",
    "1 мсMPRT",
    "1 мс(gray to gray) - Extreme Mode  Color Support",
    "2мс (GtG), 1мс (MPRT)",
    "6.5 мс",
    "1 мс (MPRT)<br>4 мс (от серого к серому) в экстремальном режиме",
    "7мс (GtG)",
    "1 ms VRB",
    "2",
    "0.4мс",
    "1 мс (VRB)",
    "7мс"
  ],
  "matrixType": [
    "IPS",
    "MVA",
    "Nano IPS",
    "P-IPS",
    "PLS",
    "S-PVA",
    "SS-IPS",
    "SVA",
    "TFT",
    "TN",
    "TN+film",
    "VA"
  ],
  "brand": [
    "2e",
    "acer",
    "aoc",
    "apple",
    "asus",
    "atis",
    "benq",
    "dahua",
    "dell",
    "eizo",
    "elo",
    "evromedia",
    "fujitsu",
    "gigabyte",
    "hanns-g",
    "hp-hewlett-packard",
    "huawei",
    "iiyama",
    "lenovo",
    "lg",
    "msi",
    "nec",
    "neovo",
    "philips",
    "qube",
    "samsung",
    "sharp",
    "terra_",
    "terris",
    "viewsonic",
    "voltronic",
    "xiaomi"
  ]
}